COPYING
MANIFEST.in
changelog
setup.py
TracAdminEnumListPlugin.egg-info/PKG-INFO
TracAdminEnumListPlugin.egg-info/SOURCES.txt
TracAdminEnumListPlugin.egg-info/dependency_links.txt
TracAdminEnumListPlugin.egg-info/entry_points.txt
TracAdminEnumListPlugin.egg-info/not-zip-safe
TracAdminEnumListPlugin.egg-info/top_level.txt
adminenumlistplugin/__init__.py
adminenumlistplugin/adminenumlistplugin.py
adminenumlistplugin/htdocs/adminenumlist.js
adminenumlistplugin/htdocs/jqueryui-1.6/jquery-ui.min.js
adminenumlistplugin/htdocs/jqueryui-1.8.24/jquery-ui.min.js