Metadata-Version: 1.1
Name: TracAdminEnumListPlugin
Version: 2.0
Summary: Adds drag-and-drop reordering to admin panel enum lists.
Home-page: http://trac-hacks.org/wiki/AdminEnumListPlugin
Author: Ryan J Ollos
Author-email: ryan.j.ollos@gmail.com
License: 3-Clause BSD
Keywords: trac plugin
Platform: UNKNOWN
Classifier: Framework :: Trac
Classifier: Development Status :: 5 - Production/Stable
Classifier: Environment :: Web Environment
Classifier: License :: OSI Approved :: BSD License
Classifier: Natural Language :: English
Classifier: Operating System :: OS Independent
Classifier: Programming Language :: Python
